odoo/addons/edi_party_data_oca/README.rst
odoo/addons/edi_party_data_oca/__init__.py
odoo/addons/edi_party_data_oca/__manifest__.py
odoo/addons/edi_party_data_oca/utils.py
odoo/addons/edi_party_data_oca/components/__init__.py
odoo/addons/edi_party_data_oca/components/common.py
odoo/addons/edi_party_data_oca/components/party_data.py
odoo/addons/edi_party_data_oca/i18n/edi_party_data_oca.pot
odoo/addons/edi_party_data_oca/models/__init__.py
odoo/addons/edi_party_data_oca/models/edi_exchange_type.py
odoo/addons/edi_party_data_oca/readme/CONFIGURE.rst
odoo/addons/edi_party_data_oca/readme/CONTRIBUTORS.rst
odoo/addons/edi_party_data_oca/readme/DESCRIPTION.rst
odoo/addons/edi_party_data_oca/readme/USAGE.rst
odoo/addons/edi_party_data_oca/static/description/icon.png
odoo/addons/edi_party_data_oca/static/description/index.html
odoo/addons/edi_party_data_oca/tests/__init__.py
odoo/addons/edi_party_data_oca/tests/test_party_data.py
odoo/addons/edi_party_data_oca/views/edi_exchange_type_views.xml
odoo14_addon_edi_party_data_oca-14.0.1.1.0.dist-info/METADATA
odoo14_addon_edi_party_data_oca-14.0.1.1.0.dist-info/WHEEL
odoo14_addon_edi_party_data_oca-14.0.1.1.0.dist-info/top_level.txt
odoo14_addon_edi_party_data_oca-14.0.1.1.0.dist-info/RECORD
