Metadata-Version: 2.1
Name: odoo14-addon-edi-party-data-oca
Version: 14.0.1.1.0
Summary: Allow to configure and retrieve party information for EDI exchanges.
Home-page: https://github.com/OCA/edi
Author: Camptocamp, Odoo Community Association (OCA)
Author-email: support@odoo-community.org
License: AGPL-3
Platform: UNKNOWN
Classifier: Programming Language :: Python
Classifier: Framework :: Odoo
Classifier: Framework :: Odoo :: 14.0
Classifier: License :: OSI Approved :: GNU Affero General Public License v3
Classifier: Development Status :: 3 - Alpha
Requires-Python: >=3.6
Requires-Dist: odoo14-addon-edi-oca
Requires-Dist: odoo14-addon-partner-identification
Requires-Dist: odoo (<14.1dev,>=14.0a)
